ai_agent/__init__.py
ai_agent/_version.py
ai_agent/agent.py
aigent_py-0.1.1.dist-info/LICENSE
aigent_py-0.1.1.dist-info/METADATA
aigent_py-0.1.1.dist-info/WHEEL
aigent_py-0.1.1.dist-info/RECORD
