Metadata-Version: 2.1
Name: aigent-py
Version: 0.1.1
Summary: An AI agent that processes natural language commands through LLM and executes corresponding actions
Home-page: https://github.com/ChefJodlak/aigent
Keywords: ai,llm,openai,commands,natural-language-processing
Author: Rafal Jodelka
Author-email: rafaljodlak@gmail.com
Requires-Python: >=3.8
Classifier: Development Status :: 3 - Alpha
Classifier: Intended Audience :: Developers
Classifier: License :: OSI Approved :: MIT License
Classifier: Programming Language :: Python :: 3
Classifier: Programming Language :: Python :: 3.8
Classifier: Programming Language :: Python :: 3.9
Classifier: Programming Language :: Python :: 3.10
Classifier: Programming Language :: Python :: 3.11
Classifier: Programming Language :: Python :: 3.12
Classifier: Programming Language :: Python :: 3.13
Requires-Dist: openai (==1.57.0)
Requires-Dist: pydantic (>=2.0.0)
Project-URL: Repository, https://github.com/ChefJodlak/aigent
